AUTHORS.rst
CONTRIBUTING.rst
HISTORY.rst
LICENSE
MANIFEST.in
README.md
setup.cfg
setup.py
legendarium/__init__.py
legendarium/formatter.py
legendarium/urlegendarium.py
legendarium/utils.py
legendarium.egg-info/PKG-INFO
legendarium.egg-info/SOURCES.txt
legendarium.egg-info/dependency_links.txt
legendarium.egg-info/not-zip-safe
legendarium.egg-info/top_level.txt