Metadata-Version: 2.1
Name: legendarium
Version: 2.0.5
Summary: Python library to handle SciELO's bibliographic strip
Home-page: https://github.com/scieloorg/legendarium
Author: Jamil Atta Junior
Author-email: jamil.atta@scielo.org
License: BSD license
Keywords: legendarium
Platform: UNKNOWN
Classifier: Development Status :: 2 - Pre-Alpha
Classifier: Intended Audience :: Developers
Classifier: License :: OSI Approved :: BSD License
Classifier: Natural Language :: English
Classifier: Programming Language :: Python :: 2.7
Classifier: Programming Language :: Python :: 3
